nlp_link/__init__.py
nlp_link/linker.py
nlp_link/linker_utils.py
nlp_link/soc_mapper/.ipynb_checkpoints/ONS_comparison-checkpoint.ipynb
nlp_link/soc_mapper/ONS_comparison.ipynb
nlp_link/soc_mapper/README.md
nlp_link/soc_mapper/SOCMapper_overview.jpg
nlp_link/soc_mapper/__init__.py
nlp_link/soc_mapper/config.yaml
nlp_link/soc_mapper/soc_map.py
nlp_link/soc_mapper/soc_map_utils.py
nlp_link/utils/utils.py
nlp_link-0.1.5.dist-info/LICENSE
nlp_link-0.1.5.dist-info/METADATA
nlp_link-0.1.5.dist-info/WHEEL
nlp_link-0.1.5.dist-info/RECORD
